ml_mdm/__about__.py
ml_mdm/core.py
tests/__init__.py
ml_mdm-0.1.0.dist-info/METADATA
ml_mdm-0.1.0.dist-info/WHEEL
ml_mdm-0.1.0.dist-info/top_level.txt
ml_mdm-0.1.0.dist-info/RECORD
