Metadata-Version: 2.2
Name: ml-mdm
Version: 0.1.0
Summary: A python package to simplify the creation of text conditioned image diffusion models
Author: Apple
Project-URL: Homepage, https://github.com/apple/ml-mdm
Project-URL: Issues, https://github.com/apple/ml-mdm
Requires-Python: >3.8
Requires-Dist: simple-parsing
